README.md
setup.py
dgnx/__init__.py
dgnx.egg-info/PKG-INFO
dgnx.egg-info/SOURCES.txt
dgnx.egg-info/dependency_links.txt
dgnx.egg-info/requires.txt
dgnx.egg-info/top_level.txt
dgnx/algorithms/__init__.py
dgnx/algorithms/algorithms.py
dgnx/classes/__init__.py
dgnx/classes/dynamicdirectedgraph.py
dgnx/readwrite/__init__.py
dgnx/utils/__init__.py
dgnx/utils/write_gexf.py