Metadata-Version: 1.0
Name: dgnx
Version: 0.1.2
Summary: Dynamic Graph NetworkX Library
Home-page: https://github.com/raitonvortex/dgnx
Author: Tiago Barbosa
Author-email: tiago.l.barbosa@tecnico.ulisboa.pt
License: BSD-Clause-2
Platform: UNKNOWN
